setup.py
huepy/__init__.py
huepy/huepy.py
huepy/test.py
huepy.egg-info/PKG-INFO
huepy.egg-info/SOURCES.txt
huepy.egg-info/dependency_links.txt
huepy.egg-info/top_level.txt